notebook_as_pdf/__init__.py
notebook_as_pdf-0.5.0.dist-info/LICENSE
notebook_as_pdf-0.5.0.dist-info/METADATA
notebook_as_pdf-0.5.0.dist-info/WHEEL
notebook_as_pdf-0.5.0.dist-info/entry_points.txt
notebook_as_pdf-0.5.0.dist-info/top_level.txt
notebook_as_pdf-0.5.0.dist-info/RECORD
