Metadata-Version: 2.1
Name: notebook-as-pdf
Version: 0.5.0
Summary: Jupyter extension to export notebooks as PDFs
Home-page: https://github.com/betatim/notebook-as-pdf
Author: Tim Head
Author-email: betatim@gmail.com
License: BSD3
Keywords: jupyter pdf export bundler
Platform: UNKNOWN
Requires-Python: >=3.7
